<?xml version="1.0" encoding="UTF-8" standalone="no"?>
<animation id="Mujer1TalkingAnimation.eaa.xml" usetransitions="no" slides="no">
  <documentation>Animation created by upgrader</documentation>
  <transition type="0" time="0" />
  <frame uri="assets/animation/Cafeteria_personaje02_habla_0029.png" type="image" time="250" waitforclick="no" soundUri="" maxSoundTime="1000">
    <documentation>
    </documentation>
  </frame>
  <transition type="0" time="0" />
  <frame uri="assets/animation/Cafeteria_personaje02_habla_0036.png" type="image" time="250" waitforclick="no" soundUri="" maxSoundTime="1000">
    <documentation>
    </documentation>
  </frame>
  <transition type="0" time="0" />
  <frame uri="assets/animation/Cafeteria_personaje02_habla_0043.png" type="image" time="250" waitforclick="no" soundUri="" maxSoundTime="1000">
    <documentation>
    </documentation>
  </frame>
  <transition type="0" time="0" />
  <frame uri="assets/animation/Cafeteria_personaje02_habla_0050.png" type="image" time="250" waitforclick="no" soundUri="" maxSoundTime="1000">
    <documentation>
    </documentation>
  </frame>
  <transition type="0" time="0" />
  <frame uri="assets/animation/Cafeteria_personaje02_habla_0001.png" type="image" time="250" waitforclick="no" soundUri="" maxSoundTime="1000">
    <documentation>
    </documentation>
  </frame>
  <transition type="0" time="0" />
  <frame uri="assets/animation/Cafeteria_personaje02_habla_0008.png" type="image" time="250" waitforclick="no" soundUri="" maxSoundTime="1000">
    <documentation>
    </documentation>
  </frame>
  <transition type="0" time="0" />
  <frame uri="assets/animation/Cafeteria_personaje02_habla_0015.png" type="image" time="250" waitforclick="no" soundUri="" maxSoundTime="1000">
    <documentation>
    </documentation>
  </frame>
  <transition type="0" time="0" />
  <frame uri="assets/animation/Cafeteria_personaje02_habla_0022.png" type="image" time="250" waitforclick="no" soundUri="" maxSoundTime="1000">
    <documentation>
    </documentation>
  </frame>
  <transition type="0" time="0" />
</animation>